apkkit/__init__.py
apkkit/portage.py
apkkit/base/__init__.py
apkkit/base/package.py
apkkit/io/__init__.py
apkkit/io/apkfile.py
apkkit/io/util.py
apkkit-0.5.1.dist-info/DESCRIPTION.rst
apkkit-0.5.1.dist-info/METADATA
apkkit-0.5.1.dist-info/RECORD
apkkit-0.5.1.dist-info/WHEEL
apkkit-0.5.1.dist-info/metadata.json
apkkit-0.5.1.dist-info/top_level.txt
