Metadata-Version: 2.0
Name: apkkit
Version: 0.5.1
Summary: Manage APK packages from Python
Home-page: http://adelielinux.org/
Author: A. Wilcox
Author-email: awilfox@adelielinux.org
License: NCSA
Keywords: apk packaging portage
Platform: UNKNOWN
Classifier: Development Status :: 3 - Alpha
Classifier: Intended Audience :: Developers
Classifier: Intended Audience :: System Administrators
Classifier: License :: OSI Approved
Classifier: Operating System :: POSIX :: Linux
Classifier: Programming Language :: Python :: 3.4
Classifier: Programming Language :: Python :: 3.5
Classifier: Programming Language :: Python :: 3.6
Classifier: Programming Language :: Python :: 3 :: Only
Classifier: Topic :: Software Development :: Libraries
Classifier: Topic :: System :: Archiving :: Packaging
Classifier: Topic :: System :: Software Distribution
Requires-Dist: cryptography
Requires-Dist: jinja
Requires-Dist: pyyaml
